class_singledispatch/__init__.py
class_singledispatch/py.typed
class_singledispatch-1.2.3.post2.dist-info/LICENSE
class_singledispatch-1.2.3.post2.dist-info/METADATA
class_singledispatch-1.2.3.post2.dist-info/WHEEL
class_singledispatch-1.2.3.post2.dist-info/RECORD
