Metadata-Version: 2.1
Name: class_singledispatch
Version: 1.2.3.post2
Summary: A ``singledispatch()`` for arguments that are classes annotated as specific types.
Home-page: https://github.com/bswck/class_singledispatch
License: MIT
Author: bswck
Author-email: bartoszpiotrslawecki@gmail.com
Requires-Python: >=3.8
Classifier: License :: OSI Approved :: MIT License
Classifier: Programming Language :: Python :: 3
Classifier: Programming Language :: Python :: 3.8
Classifier: Programming Language :: Python :: 3.9
Classifier: Programming Language :: Python :: 3.10
Classifier: Programming Language :: Python :: 3.11
Classifier: Programming Language :: Python :: 3.12
Provides-Extra: modern-type-hints
Requires-Dist: eval-type-backport (>=0.2.0) ; extra == "modern-type-hints"
Project-URL: Coverage, https://coverage-badge.samuelcolvin.workers.dev/redirect/bswck/class_singledispatch
Project-URL: Documentation, https://class-singledispatch.readthedocs.io/en/latest/
Project-URL: Distribution, https://pypi.org/project/class-singledispatch/
Project-URL: Issues, https://github.com/bswck/class_singledispatch/issues
